README.md
setup.py
DSMonitor/__init__.py
DSMonitor/async_func_monitor.py
DSMonitor/async_generator_monitor.py
DSMonitor/func_hash_cache.py
DSMonitor/func_monitor.py
DSMonitor.egg-info/PKG-INFO
DSMonitor.egg-info/SOURCES.txt
DSMonitor.egg-info/dependency_links.txt
DSMonitor.egg-info/top_level.txt
DSMonitor/utils/Exceptions.py
DSMonitor/utils/__init__.py