Metadata-Version: 2.1
Name: DSMonitor
Version: 0.1.20
Summary: A tool that allows you to dynamically observe the running status of Python programs
Home-page: https://github.com/taojinmin/DSMonitor
Author: taojinmin
Author-email: taojinmin1996@foxmail.com
License: UNKNOWN
Platform: UNKNOWN
Classifier: Programming Language :: Python :: 3
Classifier: License :: OSI Approved :: GNU General Public License v3 (GPLv3)
Classifier: Operating System :: OS Independent
